{"remainingRequest":"C:\\Ampps\\www\\wordpress\\bedrock\\web\\app\\themes\\muitu\\node_modules\\buble-loader\\index.js??ref--2-1!C:\\Ampps\\www\\wordpress\\bedrock\\web\\app\\themes\\muitu\\node_modules\\eslint-loader\\index.js!C:\\Ampps\\www\\wordpress\\bedrock\\web\\app\\themes\\muitu\\node_modules\\import-glob\\index.js!C:\\Ampps\\www\\wordpress\\bedrock\\web\\app\\themes\\muitu\\resources\\assets\\scripts\\routes\\home.js","dependencies":[{"path":"C:\\Ampps\\www\\wordpress\\bedrock\\web\\app\\themes\\muitu\\resources\\assets\\scripts\\routes\\home.js","mtime":1530334040334},{"path":"C:\\Ampps\\www\\wordpress\\bedrock\\web\\app\\themes\\muitu\\node_modules\\cache-loader\\dist\\cjs.js","mtime":0},{"path":"C:\\Ampps\\www\\wordpress\\bedrock\\web\\app\\themes\\muitu\\node_modules\\buble-loader\\index.js","mtime":1487914911000},{"path":"C:\\Ampps\\www\\wordpress\\bedrock\\web\\app\\themes\\muitu\\node_modules\\eslint-loader\\index.js","mtime":1499322156000},{"path":"C:\\Ampps\\www\\wordpress\\bedrock\\web\\app\\themes\\muitu\\node_modules\\import-glob\\index.js","mtime":1475481585000}],"contextDependencies":[],"result":["export default {\n  init: function init() {\n    // JavaScript to be fired on the home page\n    $(document).ready(function(){\n      var imgItems = $('.slider li').length; // Numero de Slides\n      var imgPos = 1;\n    \n      // Agregando paginacion --\n\n      //------------------------\n    \n      $('.slider li').hide(); // Ocultanos todos los slides\n      $('.slider li:first').show(); // Mostramos el primer slide\n      $('.pagination li:first').css({'color': '#CD6E2E'}); // Damos estilos al primer item de la paginacion\n    \n      // Ejecutamos todas las funciones\n      $('.pagination li').click(pagination);\n      $('.right span').click(nextSlider);\n      $('.left span').click(prevSlider);\n    \n    \n      setInterval(function(){\n        nextSlider();\n      }, 10000);\n    \n      // FUNCIONES =========================================================\n    \n      function pagination(){\n        var paginationPos = $(this).index() + 1; // Posicion de la paginacion seleccionada\n    \n        $('.slider li').hide(); // Ocultamos todos los slides\n        $('.slider li:nth-child('+ paginationPos +')').fadeIn(); // Mostramos el Slide seleccionado\n    \n        // Dandole estilos a la paginacion seleccionada\n        $('.pagination li').css({'color': '#858585'});\n        $(this).css({'color': '#CD6E2E'});\n    \n        imgPos = paginationPos;\n    \n      }\n    \n      function nextSlider(){\n        if( imgPos >= imgItems){imgPos = 1;} \n        else {imgPos++;}\n    \n        $('.pagination li').css({'color': '#858585'});\n        $('.pagination li:nth-child(' + imgPos +')').css({'color': '#CD6E2E'});\n    \n        $('.slider li').hide(); // Ocultamos todos los slides\n        $('.slider li').removeClass('active'); // Ocultamos la clase de todos los slides\n        $('.slider li:nth-child('+ imgPos +')').fadeIn(); // Mostramos el Slide seleccionado\n        $('.slider li:nth-child('+ imgPos +')').addClass('active'); // Mostramos la clase en el item seleccionado\n        //////////////////\n        function getAverageRGB(imgEl) {\n\n          var blockSize = 5, // only visit every 5 pixels\n              defaultRGB = {r:0,g:0,b:0}, // for non-supporting envs\n              canvas = document.createElement('canvas'),\n              context = canvas.getContext && canvas.getContext('2d'),\n              data, width, height,\n              i = -4,\n              length,\n              rgb = {r:0,g:0,b:0},\n              count = 0;\n          \n          if (!context) {\n              return defaultRGB;\n          }\n          \n          height = canvas.height = imgEl.height;\n          width = canvas.width = imgEl.width;\n          \n          context.drawImage(imgEl, 0, 0);\n          \n          try {\n              data = context.getImageData(0, 0, width, height);\n          } catch(e) {\n              /* security error, img on diff domain */\n              return defaultRGB;\n          }\n          \n          length = data.data.length;\n          \n          while ( (i += blockSize * 4) < length ) {\n              ++count;\n              rgb.r += data.data[i];\n              rgb.g += data.data[i+1];\n              rgb.b += data.data[i+2];\n          }\n          \n          // ~~ used to floor values\n          rgb.r = ~~(rgb.r/count);\n          rgb.g = ~~(rgb.g/count);\n          rgb.b = ~~(rgb.b/count);\n          \n          return rgb;\n          \n          }\n          \n          var imagen  = document.querySelector(\".active img\");\n          var rgb_promedio = getAverageRGB(imagen);\n          $('body, html').css({'background-color': 'rgba('+ rgb_promedio.r + ',' + rgb_promedio.g + ',' + rgb_promedio.b +', 0.5)' });\n      }\n    ////////////////////\n      function prevSlider(){\n        if( imgPos <= 1){imgPos = imgItems;} \n        else {imgPos--;}\n    \n        $('.pagination li').css({'color': '#858585'});\n        $('.pagination li:nth-child(' + imgPos +')').css({'color': '#CD6E2E'});\n    \n        $('.slider li').hide(); // Ocultamos todos los slides\n        $('.slider li:nth-child('+ imgPos +')').fadeIn(); // Mostramos el Slide seleccionado\n         //////////////////\n         function getAverageRGB(imgEl) {\n\n          var blockSize = 5, // only visit every 5 pixels\n              defaultRGB = {r:0,g:0,b:0}, // for non-supporting envs\n              canvas = document.createElement('canvas'),\n              context = canvas.getContext && canvas.getContext('2d'),\n              data, width, height,\n              i = -4,\n              length,\n              rgb = {r:0,g:0,b:0},\n              count = 0;\n          \n          if (!context) {\n              return defaultRGB;\n          }\n          \n          height = canvas.height = imgEl.height;\n          width = canvas.width = imgEl.width;\n          \n          context.drawImage(imgEl, 0, 0);\n          \n          try {\n              data = context.getImageData(0, 0, width, height);\n          } catch(e) {\n              /* security error, img on diff domain */\n              return defaultRGB;\n          }\n          \n          length = data.data.length;\n          \n          while ( (i += blockSize * 4) < length ) {\n              ++count;\n              rgb.r += data.data[i];\n              rgb.g += data.data[i+1];\n              rgb.b += data.data[i+2];\n          }\n          \n          // ~~ used to floor values\n          rgb.r = ~~(rgb.r/count);\n          rgb.g = ~~(rgb.g/count);\n          rgb.b = ~~(rgb.b/count);\n          \n          return rgb;\n          \n          }\n          \n          var imagen  = document.querySelector(\".active img\");\n          var rgb_promedio = getAverageRGB(imagen);\n          $('body, html').css({'background-color': 'rgba('+ rgb_promedio.r + ',' + rgb_promedio.g + ',' + rgb_promedio.b +', 0.5)' });\n\n\n          \n      }\n    });\n      $('#clickbolsos').click(function (e) { \n        e.preventDefault();\n        $('#bolsos, #hamacas, #cinturones, #pulceras').fadeOut();\n        $('#bolsos').fadeToggle();        \n      });\n      $('#clickhamacas').click(function (e) { \n        e.preventDefault();\n        $('#bolsos, #hamacas, #cinturones, #pulceras').fadeOut();\n        $('#hamacas').fadeToggle();        \n      });\n      $('#clickcinturnes').click(function (e) { \n        e.preventDefault();\n        $('#bolsos, #hamacas, #cinturones, #pulceras').fadeOut();\n        $('#cinturones').fadeToggle();        \n      });\n      $('#clickpulceras').click(function (e) { \n        e.preventDefault();\n        $('#bolsos, #hamacas, #cinturones, #pulceras').fadeOut();\n        $('#pulceras').fadeToggle();        \n      });\n\n      ////////////////////////////////////////////////////////////////////////\n\n    },\n\n  finalize: function finalize() {\n    // JavaScript to be fired on the home page, after the init JS\n  },\n};\n",{"version":3,"file":"C:\\Ampps\\www\\wordpress\\bedrock\\web\\app\\themes\\muitu\\resources\\assets\\scripts\\routes\\home.js","sources":["resources\\assets\\scripts\\routes\\home.js"],"sourcesContent":["export default {\n  init() {\n    // JavaScript to be fired on the home page\n    $(document).ready(function(){\n      var imgItems = $('.slider li').length; // Numero de Slides\n      var imgPos = 1;\n    \n      // Agregando paginacion --\n\n      //------------------------\n    \n      $('.slider li').hide(); // Ocultanos todos los slides\n      $('.slider li:first').show(); // Mostramos el primer slide\n      $('.pagination li:first').css({'color': '#CD6E2E'}); // Damos estilos al primer item de la paginacion\n    \n      // Ejecutamos todas las funciones\n      $('.pagination li').click(pagination);\n      $('.right span').click(nextSlider);\n      $('.left span').click(prevSlider);\n    \n    \n      setInterval(function(){\n        nextSlider();\n      }, 10000);\n    \n      // FUNCIONES =========================================================\n    \n      function pagination(){\n        var paginationPos = $(this).index() + 1; // Posicion de la paginacion seleccionada\n    \n        $('.slider li').hide(); // Ocultamos todos los slides\n        $('.slider li:nth-child('+ paginationPos +')').fadeIn(); // Mostramos el Slide seleccionado\n    \n        // Dandole estilos a la paginacion seleccionada\n        $('.pagination li').css({'color': '#858585'});\n        $(this).css({'color': '#CD6E2E'});\n    \n        imgPos = paginationPos;\n    \n      }\n    \n      function nextSlider(){\n        if( imgPos >= imgItems){imgPos = 1;} \n        else {imgPos++;}\n    \n        $('.pagination li').css({'color': '#858585'});\n        $('.pagination li:nth-child(' + imgPos +')').css({'color': '#CD6E2E'});\n    \n        $('.slider li').hide(); // Ocultamos todos los slides\n        $('.slider li').removeClass('active'); // Ocultamos la clase de todos los slides\n        $('.slider li:nth-child('+ imgPos +')').fadeIn(); // Mostramos el Slide seleccionado\n        $('.slider li:nth-child('+ imgPos +')').addClass('active'); // Mostramos la clase en el item seleccionado\n        //////////////////\n        function getAverageRGB(imgEl) {\n\n          var blockSize = 5, // only visit every 5 pixels\n              defaultRGB = {r:0,g:0,b:0}, // for non-supporting envs\n              canvas = document.createElement('canvas'),\n              context = canvas.getContext && canvas.getContext('2d'),\n              data, width, height,\n              i = -4,\n              length,\n              rgb = {r:0,g:0,b:0},\n              count = 0;\n          \n          if (!context) {\n              return defaultRGB;\n          }\n          \n          height = canvas.height = imgEl.height;\n          width = canvas.width = imgEl.width;\n          \n          context.drawImage(imgEl, 0, 0);\n          \n          try {\n              data = context.getImageData(0, 0, width, height);\n          } catch(e) {\n              /* security error, img on diff domain */\n              return defaultRGB;\n          }\n          \n          length = data.data.length;\n          \n          while ( (i += blockSize * 4) < length ) {\n              ++count;\n              rgb.r += data.data[i];\n              rgb.g += data.data[i+1];\n              rgb.b += data.data[i+2];\n          }\n          \n          // ~~ used to floor values\n          rgb.r = ~~(rgb.r/count);\n          rgb.g = ~~(rgb.g/count);\n          rgb.b = ~~(rgb.b/count);\n          \n          return rgb;\n          \n          }\n          \n          var imagen  = document.querySelector(\".active img\");\n          var rgb_promedio = getAverageRGB(imagen);\n          $('body, html').css({'background-color': 'rgba('+ rgb_promedio.r + ',' + rgb_promedio.g + ',' + rgb_promedio.b +', 0.5)' });\n      }\n    ////////////////////\n      function prevSlider(){\n        if( imgPos <= 1){imgPos = imgItems;} \n        else {imgPos--;}\n    \n        $('.pagination li').css({'color': '#858585'});\n        $('.pagination li:nth-child(' + imgPos +')').css({'color': '#CD6E2E'});\n    \n        $('.slider li').hide(); // Ocultamos todos los slides\n        $('.slider li:nth-child('+ imgPos +')').fadeIn(); // Mostramos el Slide seleccionado\n         //////////////////\n         function getAverageRGB(imgEl) {\n\n          var blockSize = 5, // only visit every 5 pixels\n              defaultRGB = {r:0,g:0,b:0}, // for non-supporting envs\n              canvas = document.createElement('canvas'),\n              context = canvas.getContext && canvas.getContext('2d'),\n              data, width, height,\n              i = -4,\n              length,\n              rgb = {r:0,g:0,b:0},\n              count = 0;\n          \n          if (!context) {\n              return defaultRGB;\n          }\n          \n          height = canvas.height = imgEl.height;\n          width = canvas.width = imgEl.width;\n          \n          context.drawImage(imgEl, 0, 0);\n          \n          try {\n              data = context.getImageData(0, 0, width, height);\n          } catch(e) {\n              /* security error, img on diff domain */\n              return defaultRGB;\n          }\n          \n          length = data.data.length;\n          \n          while ( (i += blockSize * 4) < length ) {\n              ++count;\n              rgb.r += data.data[i];\n              rgb.g += data.data[i+1];\n              rgb.b += data.data[i+2];\n          }\n          \n          // ~~ used to floor values\n          rgb.r = ~~(rgb.r/count);\n          rgb.g = ~~(rgb.g/count);\n          rgb.b = ~~(rgb.b/count);\n          \n          return rgb;\n          \n          }\n          \n          var imagen  = document.querySelector(\".active img\");\n          var rgb_promedio = getAverageRGB(imagen);\n          $('body, html').css({'background-color': 'rgba('+ rgb_promedio.r + ',' + rgb_promedio.g + ',' + rgb_promedio.b +', 0.5)' });\n\n\n          \n      }\n    });\n      $('#clickbolsos').click(function (e) { \n        e.preventDefault();\n        $('#bolsos, #hamacas, #cinturones, #pulceras').fadeOut();\n        $('#bolsos').fadeToggle();        \n      });\n      $('#clickhamacas').click(function (e) { \n        e.preventDefault();\n        $('#bolsos, #hamacas, #cinturones, #pulceras').fadeOut();\n        $('#hamacas').fadeToggle();        \n      });\n      $('#clickcinturnes').click(function (e) { \n        e.preventDefault();\n        $('#bolsos, #hamacas, #cinturones, #pulceras').fadeOut();\n        $('#cinturones').fadeToggle();        \n      });\n      $('#clickpulceras').click(function (e) { \n        e.preventDefault();\n        $('#bolsos, #hamacas, #cinturones, #pulceras').fadeOut();\n        $('#pulceras').fadeToggle();        \n      });\n\n      ////////////////////////////////////////////////////////////////////////\n\n    },\n\n  finalize() {\n    // JavaScript to be fired on the home page, after the init JS\n  },\n};\n"],"names":[],"mappings":"AAAA,eAAe;EACb,IAAI,eAAA,GAAG;;IAEL,CAAC,CAAC,QAAQ,CAAC,CAAC,KAAK,CAAC,UAAU;MAC1B,IAAI,QAAQ,GAAG,CAAC,CAAC,YAAY,CAAC,CAAC,MAAM,CAAC;MACtC,IAAI,MAAM,GAAG,CAAC,CAAC;;;;;;MAMf,CAAC,CAAC,YAAY,CAAC,CAAC,IAAI,EAAE,CAAC;MACvB,CAAC,CAAC,kBAAkB,CAAC,CAAC,IAAI,EAAE,CAAC;MAC7B,CAAC,CAAC,sBAAsB,CAAC,CAAC,GAAG,CAAC,CAAC,OAAO,EAAE,SAAS,CAAC,CAAC,CAAC;;;MAGpD,CAAC,CAAC,gBAAgB,CAAC,CAAC,KAAK,CAAC,UAAU,CAAC,CAAC;MACtC,CAAC,CAAC,aAAa,CAAC,CAAC,KAAK,CAAC,UAAU,CAAC,CAAC;MACnC,CAAC,CAAC,YAAY,CAAC,CAAC,KAAK,CAAC,UAAU,CAAC,CAAC;;;MAGlC,WAAW,CAAC,UAAU;QACpB,UAAU,EAAE,CAAC;OACd,EAAE,KAAK,CAAC,CAAC;;;;MAIV,SAAS,UAAU,EAAE;QACnB,IAAI,aAAa,GAAG,CAAC,CAAC,IAAI,CAAC,CAAC,KAAK,EAAE,GAAG,CAAC,CAAC;;QAExC,CAAC,CAAC,YAAY,CAAC,CAAC,IAAI,EAAE,CAAC;QACvB,CAAC,CAAC,uBAAuB,EAAE,aAAa,EAAE,GAAG,CAAC,CAAC,MAAM,EAAE,CAAC;;;QAGxD,CAAC,CAAC,gBAAgB,CAAC,CAAC,GAAG,CAAC,CAAC,OAAO,EAAE,SAAS,CAAC,CAAC,CAAC;QAC9C,CAAC,CAAC,IAAI,CAAC,CAAC,GAAG,CAAC,CAAC,OAAO,EAAE,SAAS,CAAC,CAAC,CAAC;;QAElC,MAAM,GAAG,aAAa,CAAC;;OAExB;;MAED,SAAS,UAAU,EAAE;QACnB,IAAI,MAAM,IAAI,QAAQ,CAAC,CAAC,MAAM,GAAG,CAAC,CAAC,CAAC;aAC/B,CAAC,MAAM,EAAE,CAAC,CAAC;;QAEhB,CAAC,CAAC,gBAAgB,CAAC,CAAC,GAAG,CAAC,CAAC,OAAO,EAAE,SAAS,CAAC,CAAC,CAAC;QAC9C,CAAC,CAAC,2BAA2B,GAAG,MAAM,EAAE,GAAG,CAAC,CAAC,GAAG,CAAC,CAAC,OAAO,EAAE,SAAS,CAAC,CAAC,CAAC;;QAEvE,CAAC,CAAC,YAAY,CAAC,CAAC,IAAI,EAAE,CAAC;QACvB,CAAC,CAAC,YAAY,CAAC,CAAC,WAAW,CAAC,QAAQ,CAAC,CAAC;QACtC,CAAC,CAAC,uBAAuB,EAAE,MAAM,EAAE,GAAG,CAAC,CAAC,MAAM,EAAE,CAAC;QACjD,CAAC,CAAC,uBAAuB,EAAE,MAAM,EAAE,GAAG,CAAC,CAAC,QAAQ,CAAC,QAAQ,CAAC,CAAC;;QAE3D,SAAS,aAAa,CAAC,KAAK,EAAE;;UAE5B,IAAI,SAAS,GAAG,CAAC;cACb,UAAU,GAAG,CAAC,CAAC,CAAC,CAAC,CAAC,CAAC,CAAC,CAAC,CAAC,CAAC,CAAC,CAAC,CAAC;cAC1B,MAAM,GAAG,QAAQ,CAAC,aAAa,CAAC,QAAQ,CAAC;cACzC,OAAO,GAAG,MAAM,CAAC,UAAU,IAAI,MAAM,CAAC,UAAU,CAAC,IAAI,CAAC;cACtD,IAAI,EAAE,KAAK,EAAE,MAAM;cACnB,CAAC,GAAG,CAAC,CAAC;cACN,MAAM;cACN,GAAG,GAAG,CAAC,CAAC,CAAC,CAAC,CAAC,CAAC,CAAC,CAAC,CAAC,CAAC,CAAC,CAAC,CAAC;cACnB,KAAK,GAAG,CAAC,CAAC;;UAEd,IAAI,CAAC,OAAO,EAAE;cACV,OAAO,UAAU,CAAC;WACrB;;UAED,MAAM,GAAG,MAAM,CAAC,MAAM,GAAG,KAAK,CAAC,MAAM,CAAC;UACtC,KAAK,GAAG,MAAM,CAAC,KAAK,GAAG,KAAK,CAAC,KAAK,CAAC;;UAEnC,OAAO,CAAC,SAAS,CAAC,KAAK,EAAE,CAAC,EAAE,CAAC,CAAC,CAAC;;UAE/B,IAAI;cACA,IAAI,GAAG,OAAO,CAAC,YAAY,CAAC,CAAC,EAAE,CAAC,EAAE,KAAK,EAAE,MAAM,CAAC,CAAC;WACpD,CAAC,MAAM,CAAC,EAAE;;cAEP,OAAO,UAAU,CAAC;WACrB;;UAED,MAAM,GAAG,IAAI,CAAC,IAAI,CAAC,MAAM,CAAC;;UAE1B,QAAQ,CAAC,CAAC,IAAI,SAAS,GAAG,CAAC,CAAC,GAAG,MAAM,GAAG;cACpC,EAAE,KAAK,CAAC;cACR,GAAG,CAAC,CAAC,IAAI,IAAI,CAAC,IAAI,CAAC,CAAC,CAAC,CAAC;cACtB,GAAG,CAAC,CAAC,IAAI,IAAI,CAAC,IAAI,CAAC,CAAC,CAAC,CAAC,CAAC,CAAC;cACxB,GAAG,CAAC,CAAC,IAAI,IAAI,CAAC,IAAI,CAAC,CAAC,CAAC,CAAC,CAAC,CAAC;WAC3B;;;UAGD,GAAG,CAAC,CAAC,GAAG,CAAC,CAAC,CAAC,GAAG,CAAC,CAAC,CAAC,KAAK,CAAC,CAAC;UACxB,GAAG,CAAC,CAAC,GAAG,CAAC,CAAC,CAAC,GAAG,CAAC,CAAC,CAAC,KAAK,CAAC,CAAC;UACxB,GAAG,CAAC,CAAC,GAAG,CAAC,CAAC,CAAC,GAAG,CAAC,CAAC,CAAC,KAAK,CAAC,CAAC;;UAExB,OAAO,GAAG,CAAC;;WAEV;;UAED,IAAI,MAAM,IAAI,QAAQ,CAAC,aAAa,CAAC,aAAa,CAAC,CAAC;UACpD,IAAI,YAAY,GAAG,aAAa,CAAC,MAAM,CAAC,CAAC;UACzC,CAAC,CAAC,YAAY,CAAC,CAAC,GAAG,CAAC,CAAC,kBAAkB,EAAE,OAAO,EAAE,YAAY,CAAC,CAAC,GAAG,GAAG,GAAG,YAAY,CAAC,CAAC,GAAG,GAAG,GAAG,YAAY,CAAC,CAAC,EAAE,QAAQ,EAAE,CAAC,CAAC;OAC/H;;MAED,SAAS,UAAU,EAAE;QACnB,IAAI,MAAM,IAAI,CAAC,CAAC,CAAC,MAAM,GAAG,QAAQ,CAAC,CAAC;aAC/B,CAAC,MAAM,EAAE,CAAC,CAAC;;QAEhB,CAAC,CAAC,gBAAgB,CAAC,CAAC,GAAG,CAAC,CAAC,OAAO,EAAE,SAAS,CAAC,CAAC,CAAC;QAC9C,CAAC,CAAC,2BAA2B,GAAG,MAAM,EAAE,GAAG,CAAC,CAAC,GAAG,CAAC,CAAC,OAAO,EAAE,SAAS,CAAC,CAAC,CAAC;;QAEvE,CAAC,CAAC,YAAY,CAAC,CAAC,IAAI,EAAE,CAAC;QACvB,CAAC,CAAC,uBAAuB,EAAE,MAAM,EAAE,GAAG,CAAC,CAAC,MAAM,EAAE,CAAC;;SAEhD,SAAS,aAAa,CAAC,KAAK,EAAE;;UAE7B,IAAI,SAAS,GAAG,CAAC;cACb,UAAU,GAAG,CAAC,CAAC,CAAC,CAAC,CAAC,CAAC,CAAC,CAAC,CAAC,CAAC,CAAC,CAAC,CAAC;cAC1B,MAAM,GAAG,QAAQ,CAAC,aAAa,CAAC,QAAQ,CAAC;cACzC,OAAO,GAAG,MAAM,CAAC,UAAU,IAAI,MAAM,CAAC,UAAU,CAAC,IAAI,CAAC;cACtD,IAAI,EAAE,KAAK,EAAE,MAAM;cACnB,CAAC,GAAG,CAAC,CAAC;cACN,MAAM;cACN,GAAG,GAAG,CAAC,CAAC,CAAC,CAAC,CAAC,CAAC,CAAC,CAAC,CAAC,CAAC,CAAC,CAAC,CAAC;cACnB,KAAK,GAAG,CAAC,CAAC;;UAEd,IAAI,CAAC,OAAO,EAAE;cACV,OAAO,UAAU,CAAC;WACrB;;UAED,MAAM,GAAG,MAAM,CAAC,MAAM,GAAG,KAAK,CAAC,MAAM,CAAC;UACtC,KAAK,GAAG,MAAM,CAAC,KAAK,GAAG,KAAK,CAAC,KAAK,CAAC;;UAEnC,OAAO,CAAC,SAAS,CAAC,KAAK,EAAE,CAAC,EAAE,CAAC,CAAC,CAAC;;UAE/B,IAAI;cACA,IAAI,GAAG,OAAO,CAAC,YAAY,CAAC,CAAC,EAAE,CAAC,EAAE,KAAK,EAAE,MAAM,CAAC,CAAC;WACpD,CAAC,MAAM,CAAC,EAAE;;cAEP,OAAO,UAAU,CAAC;WACrB;;UAED,MAAM,GAAG,IAAI,CAAC,IAAI,CAAC,MAAM,CAAC;;UAE1B,QAAQ,CAAC,CAAC,IAAI,SAAS,GAAG,CAAC,CAAC,GAAG,MAAM,GAAG;cACpC,EAAE,KAAK,CAAC;cACR,GAAG,CAAC,CAAC,IAAI,IAAI,CAAC,IAAI,CAAC,CAAC,CAAC,CAAC;cACtB,GAAG,CAAC,CAAC,IAAI,IAAI,CAAC,IAAI,CAAC,CAAC,CAAC,CAAC,CAAC,CAAC;cACxB,GAAG,CAAC,CAAC,IAAI,IAAI,CAAC,IAAI,CAAC,CAAC,CAAC,CAAC,CAAC,CAAC;WAC3B;;;UAGD,GAAG,CAAC,CAAC,GAAG,CAAC,CAAC,CAAC,GAAG,CAAC,CAAC,CAAC,KAAK,CAAC,CAAC;UACxB,GAAG,CAAC,CAAC,GAAG,CAAC,CAAC,CAAC,GAAG,CAAC,CAAC,CAAC,KAAK,CAAC,CAAC;UACxB,GAAG,CAAC,CAAC,GAAG,CAAC,CAAC,CAAC,GAAG,CAAC,CAAC,CAAC,KAAK,CAAC,CAAC;;UAExB,OAAO,GAAG,CAAC;;WAEV;;UAED,IAAI,MAAM,IAAI,QAAQ,CAAC,aAAa,CAAC,aAAa,CAAC,CAAC;UACpD,IAAI,YAAY,GAAG,aAAa,CAAC,MAAM,CAAC,CAAC;UACzC,CAAC,CAAC,YAAY,CAAC,CAAC,GAAG,CAAC,CAAC,kBAAkB,EAAE,OAAO,EAAE,YAAY,CAAC,CAAC,GAAG,GAAG,GAAG,YAAY,CAAC,CAAC,GAAG,GAAG,GAAG,YAAY,CAAC,CAAC,EAAE,QAAQ,EAAE,CAAC,CAAC;;;;OAI/H;KACF,CAAC,CAAC;MACD,CAAC,CAAC,cAAc,CAAC,CAAC,KAAK,CAAC,UAAU,CAAC,EAAE;QACnC,CAAC,CAAC,cAAc,EAAE,CAAC;QACnB,CAAC,CAAC,2CAA2C,CAAC,CAAC,OAAO,EAAE,CAAC;QACzD,CAAC,CAAC,SAAS,CAAC,CAAC,UAAU,EAAE,CAAC;OAC3B,CAAC,CAAC;MACH,CAAC,CAAC,eAAe,CAAC,CAAC,KAAK,CAAC,UAAU,CAAC,EAAE;QACpC,CAAC,CAAC,cAAc,EAAE,CAAC;QACnB,CAAC,CAAC,2CAA2C,CAAC,CAAC,OAAO,EAAE,CAAC;QACzD,CAAC,CAAC,UAAU,CAAC,CAAC,UAAU,EAAE,CAAC;OAC5B,CAAC,CAAC;MACH,CAAC,CAAC,iBAAiB,CAAC,CAAC,KAAK,CAAC,UAAU,CAAC,EAAE;QACtC,CAAC,CAAC,cAAc,EAAE,CAAC;QACnB,CAAC,CAAC,2CAA2C,CAAC,CAAC,OAAO,EAAE,CAAC;QACzD,CAAC,CAAC,aAAa,CAAC,CAAC,UAAU,EAAE,CAAC;OAC/B,CAAC,CAAC;MACH,CAAC,CAAC,gBAAgB,CAAC,CAAC,KAAK,CAAC,UAAU,CAAC,EAAE;QACrC,CAAC,CAAC,cAAc,EAAE,CAAC;QACnB,CAAC,CAAC,2CAA2C,CAAC,CAAC,OAAO,EAAE,CAAC;QACzD,CAAC,CAAC,WAAW,CAAC,CAAC,UAAU,EAAE,CAAC;OAC7B,CAAC,CAAC;;;;KAIJ;;EAEH,QAAQ,mBAAA,GAAG;;GAEV;CACF,CAAC;","sourceRoot":"C:\\Ampps\\www\\wordpress\\bedrock\\web\\app\\themes\\muitu"}]}